{
  "date": "2026-02-03",
  "channels": {
    "twitter": {
      "status": "ok",
      "lastFetch": "2026-02-03T20:22:19.735Z",
      "mentionCount": 4,
      "error": null
    },
    "linkedin": {
      "status": "ok",
      "lastFetch": "2026-02-03T20:22:19.735Z",
      "mentionCount": 6,
      "error": null
    },
    "ios_store": {
      "status": "ok",
      "lastFetch": "2026-02-03T20:22:19.735Z",
      "mentionCount": 50,
      "error": null
    },
    "android_store": {
      "status": "ok",
      "lastFetch": "2026-02-03T20:22:19.735Z",
      "mentionCount": 50,
      "error": null
    }
  },
  "summary": {
    "totalMentions": 110,
    "criticalIssues": 10,
    "storeRating": 2.7,
    "avgResponseTime": "N/A"
  },
  "heatmap": {
    "login": [
      2,
      1,
      1,
      2,
      0,
      0,
      0
    ],
    "transfer": [
      0,
      1,
      0,
      2,
      0,
      0,
      0
    ],
    "payment": [
      0,
      1,
      1,
      0,
      0,
      0,
      0
    ],
    "card": [
      0,
      1,
      0,
      0,
      0,
      0,
      0
    ],
    "loan": [
      0,
      0,
      0,
      0,
      0,
      0,
      0
    ],
    "investment": [
      0,
      1,
      0,
      0,
      0,
      0,
      0
    ],
    "account": [
      0,
      0,
      0,
      0,
      0,
      0,
      0
    ],
    "notification": [
      0,
      0,
      0,
      0,
      0,
      0,
      0
    ],
    "atm": [
      0,
      0,
      0,
      1,
      0,
      0,
      0
    ],
    "insurance": [
      0,
      0,
      0,
      0,
      0,
      0,
      0
    ],
    "pension": [
      0,
      0,
      0,
      0,
      0,
      0,
      0
    ],
    "hgs": [
      0,
      0,
      0,
      0,
      0,
      0,
      0
    ],
    "bill": [
      0,
      0,
      0,
      0,
      0,
      0,
      0
    ],
    "appointment": [
      0,
      0,
      0,
      0,
      0,
      0,
      0
    ],
    "customer_service": [
      0,
      0,
      0,
      0,
      0,
      0,
      0
    ],
    "security": [
      0,
      0,
      0,
      0,
      0,
      0,
      0
    ],
    "performance": [
      0,
      0,
      0,
      0,
      0,
      0,
      0
    ],
    "ui": [
      0,
      0,
      0,
      0,
      0,
      0,
      0
    ],
    "feature": [
      0,
      0,
      0,
      0,
      0,
      0,
      2
    ],
    "other": [
      0,
      0,
      0,
      1,
      0,
      0,
      3
    ]
  },
  "days": [
    "Pzt",
    "Sal",
    "Car",
    "Per",
    "Cum",
    "Cmt",
    "Paz"
  ],
  "issues": [
    {
      "id": "issue-transfer",
      "title": "Atm sorunu Atm para veremiyorsa eft işlemlerinden ",
      "channel": "ios_store",
      "version": "N/A",
      "category": "transfer",
      "impact": "Kritik",
      "status": "Devam ediyor",
      "duration": "1+ gun",
      "commentCount": 10,
      "comments": [
        {
          "id": "ios-13704096927",
          "text": "Atm sorunu Atm para veremiyorsa eft işlemlerinden para almamalısınız.",
          "author": "hasancilek",
          "rating": 1,
          "category": "transfer",
          "channel": "ios_store",
          "sentiment": "negative"
        },
        {
          "id": "ios-13703678367",
          "text": "Maaş müsterisinden işlem ücreti alınamaz Maaş müşterisi olmamızdan dolayı para transferinde 16 lira işlem ücreti alınması adil değil.",
          "author": "Sessizlik seven",
          "rating": 1,
          "category": "transfer",
          "channel": "ios_store",
          "sentiment": "negative"
        },
        {
          "id": "ios-13703632587",
          "text": "Maas hesabim ama eft havale ucreti kesiyor Maas hesabim ama ucret kesiyor kullanmicam bankayi",
          "author": "Makfkskdksk",
          "rating": 1,
          "category": "transfer",
          "channel": "ios_store",
          "sentiment": "negative"
        },
        {
          "id": "ios-13693512987",
          "text": "Eft ücreti Hiç çalışmadan 10 tl eft ücreti teşekkürler sizinlede çalışmıyoruz artık…",
          "author": "zafer parlar.",
          "rating": 1,
          "category": "transfer",
          "channel": "ios_store",
          "sentiment": "negative"
        },
        {
          "id": "ios-13692349052",
          "text": "Eft havale Ücret almanız çok ama çok ayıp zanen sizde zaten kazanıyorsunuz",
          "author": "Fearleşlord",
          "rating": 1,
          "category": "transfer",
          "channel": "ios_store",
          "sentiment": "negative"
        },
        {
          "id": "ios-13691904668",
          "text": "Para transfer ücretleri 2 bin tl ye 8 tl kestiniz hakkım haram olsun",
          "author": "Mert__13",
          "rating": 1,
          "category": "transfer",
          "channel": "ios_store",
          "sentiment": "negative"
        },
        {
          "id": "ios-13691860727",
          "text": "Şikayet Emekliyim 17 TL eft ücreti alınıyor",
          "author": "Şikayetskn",
          "rating": 1,
          "category": "transfer",
          "channel": "ios_store",
          "sentiment": "negative"
        },
        {
          "id": "ios-13689055188",
          "text": "Havale ücreti Bu zamanda havale ücretimi kaldı ya yıl 2026",
          "author": "CanerKul",
          "rating": 1,
          "category": "transfer",
          "channel": "ios_store",
          "sentiment": "negative"
        },
        {
          "id": "android-13ebe7de-f9d8-4195-97e0-5081e12c855a",
          "text": "berbat bir uygulama sabahtan beri giremiyorum kirk dereden su getirtiyor yine olmuyor yardim bolumunden mesaj gonderiyorum diyor gelmiyor mesaj falan da.",
          "author": "Yusuf Kocaman",
          "rating": 1,
          "timestamp": "2026-01-30T22:22:49.726Z",
          "category": "transfer",
          "channel": "android_store",
          "sentiment": "negative"
        },
        {
          "id": "android-b1b5b33c-86cc-4001-afed-660a54ad8315",
          "text": "Maaş musterisiyim neden belli bir saatten sonra para transferinde ücret ödüyorum ?Bu fırsatçılık başka bir açıklaması yok .Bu uygulama birçok bankada yok bu arada",
          "author": "hülya topal",
          "rating": 1,
          "timestamp": "2026-01-20T18:57:56.605Z",
          "category": "transfer",
          "channel": "android_store",
          "sentiment": "negative"
        }
      ]
    },
    {
      "id": "issue-payment",
      "title": "GARANTİDEN ENGELLİYİM 12-13 sene once sabit bir se",
      "channel": "ios_store",
      "version": "N/A",
      "category": "payment",
      "impact": "Kritik",
      "status": "Devam ediyor",
      "duration": "1+ gun",
      "commentCount": 12,
      "comments": [
        {
          "id": "ios-13700482212",
          "text": "GARANTİDEN ENGELLİYİM 12-13 sene once sabit bir sebeb gostermeden hesaplarimi politikalari nedeniyle kapatti hala acmiyor.  Sebebi de yok. Ne borcum vardi ne de oyle bisey. Beni engellemisler subeden ",
          "author": "Erol incel",
          "rating": 1,
          "category": "payment",
          "channel": "ios_store",
          "sentiment": "negative"
        },
        {
          "id": "ios-13688226978",
          "text": "Saygısızlık ve ilğilisizler Küçükyalı şubesi memurları çok saygısız alaylı konuşmaları bir şey soruyorsun cevap yok",
          "author": "veratesisat",
          "rating": 1,
          "category": "payment",
          "channel": "ios_store",
          "sentiment": "negative"
        },
        {
          "id": "android-d3995ac5-3454-43d8-8213-9a7e91756ed2",
          "text": "cep telefonuyla ekran görüntüsü alamama sorununu ne zaman çözeceksiniz? Bu konu ciddi bir sorun olmaya başladı. Bu gerçekten bir güvenlik önlemi olsaydı laptoptan da ekran görüntüsü alamamamız gerekir",
          "author": "banu bora",
          "rating": 1,
          "timestamp": "2026-01-27T08:03:10.494Z",
          "category": "payment",
          "channel": "android_store",
          "sentiment": "negative"
        },
        {
          "id": "android-72834ea8-b5a9-48a6-94c2-bea887f0df4d",
          "text": "internetim açık olduğu halde internet bağlantınız yok diye hata veriyor ekran görüntüsü alıp şikayet edeceğim ama ekran görüntüsü de alınamıyor maalesef insanları rezil etmekten başka birşeye yaramiyo",
          "author": "Oğuzhan Tursun",
          "rating": 1,
          "timestamp": "2026-01-27T07:05:17.533Z",
          "category": "payment",
          "channel": "android_store",
          "sentiment": "negative"
        },
        {
          "id": "android-c3d4f313-b36a-4211-9f21-6f2f4972025e",
          "text": "Daha akbank kadar işlevsel bir mobil bankacılık görmedim. Garanti kadar da işlevsiz bir mobil bankacılık görmedim. Herhangi bir kredi kartı işlemi gercekleştıremiyorsunuz ne taksit seçeneği veriyor ne",
          "author": "Şükran Alkan",
          "rating": 1,
          "timestamp": "2026-01-18T12:05:46.227Z",
          "category": "payment",
          "channel": "android_store",
          "sentiment": "negative"
        },
        {
          "id": "android-70385bc0-2eef-4217-91f9-35138ea26184",
          "text": "Uygulama arayüzü kullanışsız. Öncelikle sanal kart, ana karta bağlı bir kart olmasına rağmen neden diğer bankalar gibi bu kartla yapılan harcamalarnormal ana kartın içinde gösterilmiyor. Kart borcumu ",
          "author": "AHMET KURTOĞLU",
          "rating": 1,
          "timestamp": "2025-12-12T14:04:06.889Z",
          "category": "payment",
          "channel": "android_store",
          "sentiment": "negative"
        },
        {
          "id": "android-48d2b13c-e347-4ecb-87ba-16000305c894",
          "text": "telefonu xiaomi hyper os 3.0.2.0 sürümüne güncelledim, garanti uygulaması artık açılmıyor. acil düzeltilmesi gerekli",
          "author": "Baybora Tuğrul",
          "rating": 2,
          "timestamp": "2026-01-30T15:48:31.652Z",
          "category": "payment",
          "channel": "android_store",
          "sentiment": "negative"
        },
        {
          "id": "android-2df749d7-c59f-467b-9e89-3586ce712e99",
          "text": "Samsung S23 Ultra cihazımda aşırı pil kullanımı mevcut, %51 seviyelerinde kullanim var, şarjım yarim gün gitmiyor. çözüm ve yardım rica ederiz.",
          "author": "Ömer ÖZTEMÜR",
          "rating": 1,
          "timestamp": "2026-01-29T19:50:08.160Z",
          "category": "payment",
          "channel": "android_store",
          "sentiment": "negative"
        },
        {
          "id": "android-083cc7ab-052d-4d6f-b163-acefb46ac548",
          "text": "garanti bankasi emeklisi uygulamadan basvuru yapamiyor. boyle sacmalik olurmu bankada maasiniz bulunmamaktadir cikiyor. 25 yil garanti bankasida calisiyosun maasini garanti bankasindan aliyosun bankan",
          "author": "Cihan Yenidünya",
          "rating": 1,
          "timestamp": "2026-01-16T06:02:54.521Z",
          "category": "payment",
          "channel": "android_store",
          "sentiment": "negative"
        },
        {
          "id": "android-5cb69861-40d9-4f41-b2cf-94d72c2d023c",
          "text": "Son güncelleme- 9 aralık 2025, v 17.1- ile uygulama sürekli arka planda çalışıyor ve pili çok hızlı tüketiyor. Ciddi bir problem var. ---- 10 ocak Ek yorum: Bankanın problemle ciddi şekilde ilgilendiğ",
          "author": "Uğur Ünlüakın",
          "rating": 2,
          "timestamp": "2026-01-11T09:34:06.502Z",
          "category": "payment",
          "channel": "android_store",
          "sentiment": "negative"
        }
      ]
    },
    {
      "id": "issue-card",
      "title": "Sanal kart sorunu Banka birden fazla kredi kartı v",
      "channel": "ios_store",
      "version": "N/A",
      "category": "card",
      "impact": "Kritik",
      "status": "Devam ediyor",
      "duration": "1+ gun",
      "commentCount": 6,
      "comments": [
        {
          "id": "ios-13693663313",
          "text": "Sanal kart sorunu Banka birden fazla kredi kartı veriyor ancak her kredi kartına sanal kart vermiyor, ikinci bir karta sanal kart üretmek için ilk kartın sanalını iptal ettiriyor, çok anlamsız bir uyg",
          "author": "Apapse",
          "rating": 1,
          "category": "card",
          "channel": "ios_store",
          "sentiment": "negative"
        },
        {
          "id": "ios-13689348802",
          "text": "Şikayet! İğrenç bir müşteri hizmetleriniz var. İğrenç bir mobil uygulamanız var hesabıma para attığım halde hesabım kartım olduğu halde işlem yapamadım müşteri hizmetlerine bağlanamadım gerçekten çok ",
          "author": "GZeynepG",
          "rating": 1,
          "category": "card",
          "channel": "ios_store",
          "sentiment": "negative"
        },
        {
          "id": "android-4fc3eea0-e76e-4d49-952a-8e89361512cc",
          "text": "2 defadır aynı sorun . İnternet bağlantısı yoktur diyor. Müşteri hizmetleri ile konuşup yeniden yüklüyorum 2 gün sonra gene açılmıyor. nasıl bir güncelleme yaptıysanız bonus flash uygulamasıda çalışmı",
          "author": "hüseyingencer",
          "rating": 1,
          "timestamp": "2026-01-27T05:33:10.784Z",
          "category": "card",
          "channel": "android_store",
          "sentiment": "negative"
        },
        {
          "id": "android-3e428bd1-febf-4252-87d3-a449706f6a06",
          "text": "Kredi kartımı iptal etmek istiyorum,yapay zeka asistanınızdan bu konuda destek aliyorum fakat ikisi senkronize degil. Asistanın dedigi yerde o buton bulunmuyor",
          "author": "Caner Coşkun",
          "rating": 1,
          "timestamp": "2026-01-29T20:08:39.323Z",
          "category": "card",
          "channel": "android_store",
          "sentiment": "negative"
        },
        {
          "id": "android-3446cd1f-08da-4320-b7ec-76f29c451e05",
          "text": "Taksitle beyaz eşya almak için kredi kartı limitini 150000 TL 'ye yükseltmek için talepte bulundum. Diğer bankalardaki limiti de düşürttüğüm halde yanıt alamadım. Bir problemim olmadığı halde sorunum",
          "author": "Süleyman Keskin",
          "rating": 1,
          "timestamp": "2026-01-09T12:15:45.891Z",
          "category": "card",
          "channel": "android_store",
          "sentiment": "negative"
        },
        {
          "id": "android-568492e2-73d6-4522-8e77-3534fe471cbc",
          "text": "Kredi karti harcama kısmı cok anlasilir degil..Yaptigim harcamalar dijital ve asil kart net olarak anlaşılmıyor..Yapi Kredi mobil uygulamasi daha anlasilir ve net..lutfen guncelleme ile duzeltin",
          "author": "ENES EYİGÜN",
          "rating": 1,
          "timestamp": "2026-01-13T15:12:35.537Z",
          "category": "card",
          "channel": "android_store",
          "sentiment": "negative"
        }
      ]
    },
    {
      "id": "issue-account",
      "title": "Mustafa Benim ek hesabım neden açılmıyor",
      "channel": "ios_store",
      "version": "N/A",
      "category": "account",
      "impact": "Orta",
      "status": "Devam ediyor",
      "duration": "1+ gun",
      "commentCount": 2,
      "comments": [
        {
          "id": "ios-13692964144",
          "text": "Mustafa Benim ek hesabım neden açılmıyor",
          "author": "Ek hesap açın bana",
          "rating": 1,
          "category": "account",
          "channel": "ios_store",
          "sentiment": "negative"
        },
        {
          "id": "android-3efb8830-1db8-4a2f-9a36-380546cbbe46",
          "text": "1. Uygulama zaman zaman açılmıyor, 2. varlıklarım hesaplamaları garip şekilde yanlış yapılmış görünüyor neden sonra düzeliyor. 3. Emekli aylığı aldığım bu banka K.K. yıllık ücreti kesiliyor farkedip i",
          "author": "İstanbul Cepte",
          "rating": 1,
          "timestamp": "2026-01-12T09:25:29.371Z",
          "category": "account",
          "channel": "android_store",
          "sentiment": "negative"
        }
      ]
    },
    {
      "id": "issue-atm",
      "title": "İlgi Şubelerinizde ilgi alaka problem sorun çözme ",
      "channel": "ios_store",
      "version": "N/A",
      "category": "atm",
      "impact": "Orta",
      "status": "Devam ediyor",
      "duration": "1+ gun",
      "commentCount": 2,
      "comments": [
        {
          "id": "ios-13692252762",
          "text": "İlgi Şubelerinizde ilgi alaka problem sorun çözme sıfır",
          "author": "Qvkfkdşidjfjckcmckfk",
          "rating": 1,
          "category": "atm",
          "channel": "ios_store",
          "sentiment": "negative"
        },
        {
          "id": "android-038265db-b0d3-45e5-96ca-35d7d333b3b1",
          "text": "kullandığım en yavaş en karışık en pratik olmayan banka uygulaması. nasıl oluyorsa garanti şubelerinde işlemler de çok yavaş",
          "author": "Zeynep Şensoyer",
          "rating": 1,
          "timestamp": "2026-01-31T18:14:39.853Z",
          "category": "atm",
          "channel": "android_store",
          "sentiment": "negative"
        }
      ]
    },
    {
      "id": "issue-customer_service",
      "title": "Şikayet Müşteri temsilcisine bağlanamıyorum kapanı",
      "channel": "ios_store",
      "version": "N/A",
      "category": "customer_service",
      "impact": "Orta",
      "status": "Devam ediyor",
      "duration": "1+ gun",
      "commentCount": 2,
      "comments": [
        {
          "id": "ios-13691806276",
          "text": "Şikayet Müşteri temsilcisine bağlanamıyorum kapanıyor hiçbir şekilde ulaşamıyorum berbat",
          "author": "Çok kötü garanti",
          "rating": 1,
          "category": "customer_service",
          "channel": "ios_store",
          "sentiment": "negative"
        },
        {
          "id": "android-b12cf19a-d356-43c4-a112-b937db88d0d8",
          "text": "garanti bankası müşterisiyim. yildim artık garanti banka mobile gurememekten. bu nedir ya. sürekli uygulamayı kaldır tekrar indir yapıyorum . lütfen ilgilenin niye böyle oluyor",
          "author": "Yasemin Birol",
          "rating": 1,
          "timestamp": "2026-01-26T01:42:14.750Z",
          "category": "customer_service",
          "channel": "android_store",
          "sentiment": "negative"
        }
      ]
    },
    {
      "id": "issue-notification",
      "title": "Uygulama ikonu Sürekli bildirim işareti kalıyor gi",
      "channel": "ios_store",
      "version": "N/A",
      "category": "notification",
      "impact": "Yuksek",
      "status": "Devam ediyor",
      "duration": "1+ gun",
      "commentCount": 3,
      "comments": [
        {
          "id": "ios-13689214277",
          "text": "Uygulama ikonu Sürekli bildirim işareti kalıyor gitmiyor",
          "author": "Keroskomergana",
          "rating": 2,
          "category": "notification",
          "channel": "ios_store",
          "sentiment": "negative"
        },
        {
          "id": "android-d35bef7a-84cb-4c7c-80bf-683b7e804443",
          "text": "uygulamadan sürekli Birlikte Yaparız diye bildirim geliyor. saat başı ve bazen üst üste. birkaç gündür devam ediyor. çok rahatsız edici. bunu düzeltin lütfen. uygulamanın bildirimlerini kapatmak istem",
          "author": "Melike Açari",
          "rating": 1,
          "timestamp": "2026-01-04T05:53:26.878Z",
          "category": "notification",
          "channel": "android_store",
          "sentiment": "negative"
        },
        {
          "id": "android-fbdd64b3-e378-410a-91ba-d22c244dbb74",
          "text": "2 gündür abartısız en az 100 kere \"birlikte yaparız\" diye bildirim alıyorum. Galiba artık uygulamayı sileceğim ve başaramayacağız.",
          "author": "Barış Ulusoy",
          "rating": 1,
          "timestamp": "2026-01-09T07:16:42.153Z",
          "category": "notification",
          "channel": "android_store",
          "sentiment": "negative"
        }
      ]
    },
    {
      "id": "issue-login",
      "title": "telefonuma format attım mobil uygulamayı yükledim ",
      "channel": "android_store",
      "version": "N/A",
      "category": "login",
      "impact": "Kritik",
      "status": "Devam ediyor",
      "duration": "1+ gun",
      "commentCount": 10,
      "comments": [
        {
          "id": "android-57cec51d-71bf-40f6-aeee-923840bb1112",
          "text": "telefonuma format attım mobil uygulamayı yükledim ama giriş yap ekranında beyaz ekran hatası veriyor giriş yap kısmı hiç açılmıyor bonus flaş tekrar yükledim sorunsuz açıldı çalışıyor ama mobil bankac",
          "author": "EYÜP KARAAĞAÇ",
          "rating": 1,
          "timestamp": "2026-01-26T16:58:57.366Z",
          "category": "login",
          "channel": "android_store",
          "sentiment": "negative"
        },
        {
          "id": "android-acee6127-060e-4142-ada4-283fca075cf4",
          "text": "uygulama kullanım kolaylığı sunuyor ancak şifre yenilemek istiyorum ve uygulama sürekli hata veriyor. başka telefon denedim ve yine olmuyor. uygulama da sorun var",
          "author": "Hayrettin Keles",
          "rating": 2,
          "timestamp": "2026-01-27T19:15:16.386Z",
          "category": "login",
          "channel": "android_store",
          "sentiment": "negative"
        },
        {
          "id": "android-7aba83cb-bbdf-44df-b727-f4e1709a2b7c",
          "text": "mobil şifremi unuttum, kartım yok yeni kimlik kartı ile parola ala girdiğimde kimliğimi okuduğu halde okunamadı emsalinden hatalar veriyor , birkaç telefondan daha denedim olmuyor hata veriyor bence d",
          "author": "İbrahim Ermeç",
          "rating": 1,
          "timestamp": "2026-01-30T12:30:40.810Z",
          "category": "login",
          "channel": "android_store",
          "sentiment": "negative"
        },
        {
          "id": "android-e624bc31-d73d-41c9-a643-19ff8240ceed",
          "text": "Cep şubesi uygulamasına telefonuma atılan format sonrası tekrar uygulamayı yüklediğimde yıllardır müşterisi olmama rağmen giriş yapamıyorum lütfen destek sağlar mısın ?",
          "author": "Selin Şen",
          "rating": 1,
          "timestamp": "2026-01-23T21:41:20.283Z",
          "category": "login",
          "channel": "android_store",
          "sentiment": "negative"
        },
        {
          "id": "android-eaea12ba-c5a6-4007-992b-6a429bc418a5",
          "text": "1-Önceden yaklaşan para akışı bilgisini gösterirdi. Oysa şimdi, 10 gün sonra kayıtlı ve sabit ödemeler olduğu halde \"yaklaşan ödeme yok\" diyor. Bu hata aylardır devam ediyor. 2-Telefon numaram kayıtlı",
          "author": "Tunç Işın",
          "rating": 2,
          "timestamp": "2025-12-27T10:06:13.980Z",
          "category": "login",
          "channel": "android_store",
          "sentiment": "negative"
        },
        {
          "id": "android-84cf8c61-b57c-48ea-ac7b-1c70a73b104c",
          "text": "Kaç gündür mobil uygulamaya giriş yapamıyorum. Bonus flasha girebiliyorum ama. Bu ne saçmalıktır. Müsteri iletisim merkezinde sesli ananso mobile giriş yapamıyorum diyorum, çözüm saglayabilmek için mo",
          "author": "Ertuğrul BICAKCI",
          "rating": 1,
          "timestamp": "2025-12-28T08:59:48.759Z",
          "category": "login",
          "channel": "android_store",
          "sentiment": "negative"
        },
        {
          "id": "android-d239503f-f60e-4e77-90d3-2bdb272327fb",
          "text": "uygulama da sıkıntı var her gün giriş yaparken şu anda hizmet veremiyoruz yanıtını alıyorum siliyorum tekrar yüklüyorum sonra düzeliyor. Bu problemi bir an önce çözün lütfen",
          "author": "Tuğçe Kurtulmuş",
          "rating": 1,
          "timestamp": "2026-01-28T09:38:07.545Z",
          "category": "login",
          "channel": "android_store",
          "sentiment": "negative"
        },
        {
          "id": "android-c0b56814-f673-4f5a-bd3d-975a13de4894",
          "text": "hesabıma giriş yapamıyorum haftalardır. yardım merkezi de hata veriyor. çok fazla mağdur oldum. ilk fırsatta bütün ilişiğimi keseceğim artık. kesinlikle tavsiye etmiyorum. zaten uygulam aşırı yavaştı ",
          "author": "Hasan ÇELİK",
          "rating": 1,
          "timestamp": "2026-01-30T20:43:27.524Z",
          "category": "login",
          "channel": "android_store",
          "sentiment": "negative"
        },
        {
          "id": "android-0b1a6261-305b-4770-b987-8d1277d3e3d4",
          "text": "yeni telefona yükledim ama giriş ekranı boş. herhangi bir giriş butonu yada bilgi girişi satırı yok",
          "author": "Emine",
          "rating": 2,
          "timestamp": "2026-01-31T20:18:16.395Z",
          "category": "login",
          "channel": "android_store",
          "sentiment": "negative"
        },
        {
          "id": "android-96d15972-0945-4557-bbd3-3ab65b4abe3c",
          "text": "Hiçbir işe yaramaz iphone 8 model telefonumda uygulamayı açamıyorum beyaz ekran hatası veriyor hiçbir şekilde giriş yapamıyorum cihaz için uyumludur diyor sürümü uyumludur diyor ama beyaz ekran hatası",
          "author": "ZEKİEMRE",
          "rating": 1,
          "timestamp": "2026-01-20T07:14:11.666Z",
          "category": "login",
          "channel": "android_store",
          "sentiment": "negative"
        }
      ]
    },
    {
      "id": "issue-investment",
      "title": "Bu nasıl uygulama redmi note 11 pro 5g kullanıyoru",
      "channel": "android_store",
      "version": "N/A",
      "category": "investment",
      "impact": "Orta",
      "status": "Devam ediyor",
      "duration": "1+ gun",
      "commentCount": 2,
      "comments": [
        {
          "id": "android-b557e5c4-943a-4a24-83b5-c83df2568857",
          "text": "Bu nasıl uygulama redmi note 11 pro 5g kullanıyorum uygulama sürekli beyaz ekran düşüyor silip yüklüyoruz hep aynı işlem birde yatırım hesabına geçiyorum dön babam dön bu ne biçim bir iş",
          "author": "DOĞAN TÜRKOĞLU",
          "rating": 1,
          "timestamp": "2026-01-29T17:44:41.716Z",
          "category": "investment",
          "channel": "android_store",
          "sentiment": "negative"
        },
        {
          "id": "android-3a9e8e95-aa03-4bb8-915f-9ad38dc93ba3",
          "text": "son zamanlarda Garanti bbva Mobil yatırım portföy hisse senedi alım satım ekranı donuyor evet çok yavaşladı bu konuya bir el atarsanız sevinirim",
          "author": "KAMİL KAMİL",
          "rating": 1,
          "timestamp": "2026-01-06T05:05:10.248Z",
          "category": "investment",
          "channel": "android_store",
          "sentiment": "negative"
        }
      ]
    },
    {
      "id": "issue-loan",
      "title": "uygulamaya giremiyorum 1 haftadır ' işleminizi ger",
      "channel": "android_store",
      "version": "N/A",
      "category": "loan",
      "impact": "Yuksek",
      "status": "Devam ediyor",
      "duration": "1+ gun",
      "commentCount": 3,
      "comments": [
        {
          "id": "android-b52abaf9-d5d6-4cb4-aeae-6e3db45efe31",
          "text": "uygulamaya giremiyorum 1 haftadır ' işleminizi gerçekleştiremiyoruz , lütfen daha sonra tekrar deneyin' uyarısı alıyorum",
          "author": "Melisa Yavas",
          "rating": 2,
          "timestamp": "2026-01-25T16:49:57.673Z",
          "category": "loan",
          "channel": "android_store",
          "sentiment": "negative"
        },
        {
          "id": "android-a14ce7f3-dd24-47c3-a4b3-eff410dec0c9",
          "text": "hesab açtığım şube dışında bankamatik den para çekiyorum ve bunun için hizmet bedeli kesiliyor. dünyanın hiç bir yerinde yok bu uygulama sonuçta başka bir bankadan değil garantiyi kullanıyorum. böyle ",
          "author": "Emre Karakaya",
          "rating": 1,
          "timestamp": "2025-12-26T07:41:18.272Z",
          "category": "loan",
          "channel": "android_store",
          "sentiment": "negative"
        },
        {
          "id": "android-f05985c1-ed8d-42fe-850d-d02ea657da5c",
          "text": "Kredi çekmek için uygulamaya girdim yılbaşından 1 gün önce 3 oranda kredi verirken şimdi 7.50 oranlarında veriyor bu ne saçmalık. bu düpedüz adam dolandırmak. 8 günde bu kadar yüksek oranda kredi verm",
          "author": "Onur Topkara",
          "rating": 1,
          "timestamp": "2026-01-09T20:15:15.401Z",
          "category": "loan",
          "channel": "android_store",
          "sentiment": "negative"
        }
      ]
    }
  ]
}